{
  "preview": "Новый заказ!",
  "imageOne": "/images/Rectangle 66-1.jpg",
  "imageTwo": "/images/Vector.png",
  "logo": "/images/logo 1 2.png",
  "heading": "У вас новый заказ!",
  "textOne": "Пожалуйста, свяжитесь с клиентом по указанному номеру телефона. Если клиент не ответил, свяжитесь с ним по указанной ниже почте.\n\nЧтобы посмотреть заказ клиена – перейдите по ссылке ниже. В окне конфигуратора введите пароль администратора. После вы сможете отредактировать, предоставить скидку и подтвердить заказ, отправив смету клиенту на почту.",
  "textTwo": "Конфигуратор\nкартинг клуба Le Mans",
  "lemans": "картинг клуб Le Mans",
  "order": "Заказ"
}
